{
	"description": "项目配置文件。",
	"setting": {
		"urlCheck": true,
		"es6": false,
		"postcss": true,
		"minified": true,
		"newFeature": true
	},
	"miniprogramRoot": "dist/",
	"compileType": "miniprogram",
	"appid": "wx212ce8e249e36ef4",
	"projectname": "%E4%B8%AD%E4%BA%A4%E6%9C%8D%E5%8A%A1%E5%B9%B3%E5%8F%B0",
	"libVersion": "2.2.5",
	"condition": {
		"search": {
			"current": -1,
			"list": []
		},
		"conversation": {
			"current": -1,
			"list": []
		},
		"game": {
			"currentL": -1,
			"list": []
		},
		"miniprogram": {
			"current": -1,
			"list": []
		}
	}
}